LICENSE.txt
MANIFEST
MANIFEST.in
README.txt
alltests.py
ez_setup.py
lbPG-tutorial.PDB
setup.py
PalmDB/PDBConvert.py
PalmDB/PalmDatabase.py
PalmDB/PluginManager.py
PalmDB/ToTreeline.xsl
PalmDB/Util.py
PalmDB/__init__.py
PalmDB.egg-info/PKG-INFO
PalmDB.egg-info/SOURCES.txt
PalmDB.egg-info/dependency_links.txt
PalmDB.egg-info/entry_points.txt
PalmDB.egg-info/requires.txt
PalmDB.egg-info/top_level.txt
PalmDB.egg-info/zip-safe
PalmDB/Plugins/BasePlugin.py
PalmDB/Plugins/PalmToDoPlugin.py
PalmDB/Plugins/ProgectPlugin.py
PalmDB/Plugins/ProgectXSLT_GanttProject.py
PalmDB/Plugins/ProgectXSLT_Treeline.py
PalmDB/Plugins/__init__.py
UnitTests/PluginManagerTest.py
UnitTests/UtilTest.py
UnitTests/__init__.py
